sanpo/__init__.py
sanpo/command.py
sanpo/sanitize.py
sanpo-0.3.0.dist-info/METADATA
sanpo-0.3.0.dist-info/WHEEL
sanpo-0.3.0.dist-info/entry_points.txt
sanpo-0.3.0.dist-info/licenses/LICENSE
sanpo-0.3.0.dist-info/RECORD
