Metadata-Version: 2.4
Name: sanpo
Version: 0.3.0
Summary: Sanitize PO files from gettext for version control
Project-URL: Homepage, https://github.com/roskakori/sanpo
Project-URL: Repository, https://github.com/roskakori/sanpo.git
Project-URL: Issue Tracker, https://github.com/roskakori/sanpo/issues
Project-URL: Changes, https://github.com/roskakori/sanpo/blob/main/CHANGES.md
Author-email: Thomas Aglassinger <roskakori@users.sourceforge.net>
License-Expression: BSD-3-Clause
License-File: LICENSE
Keywords: clean,gettext,po,sanitize
Classifier: Development Status :: 4 - Beta
Classifier: Environment :: Console
Classifier: Intended Audience :: Developers
Classifier: License :: OSI Approved :: BSD License
Classifier: Natural Language :: English
Classifier: Operating System :: OS Independent
Classifier: Programming Language :: Python :: 3 :: Only
Classifier: Programming Language :: Python :: 3.10
Classifier: Programming Language :: Python :: 3.11
Classifier: Programming Language :: Python :: 3.12
Classifier: Programming Language :: Python :: 3.13
Classifier: Programming Language :: Python :: 3.14
Classifier: Programming Language :: Python :: 3.15
Classifier: Topic :: Software Development :: Build Tools
Classifier: Topic :: Software Development :: Internationalization
Classifier: Topic :: Software Development :: Version Control
Requires-Python: <4,>=3.10
Requires-Dist: chardet<6,>=5
Requires-Dist: pygments<3,>=2
